LICENSE
MANIFEST.in
README.rst
setup.py
twless/__init__.py
twless/channel.py
twless/context.py
twless/defer.py
twless/error.py
twless/metrics.py
twless/schedule.py
twless/tasklet.py
twless.egg-info/PKG-INFO
twless.egg-info/SOURCES.txt
twless.egg-info/dependency_links.txt
twless.egg-info/requires.txt
twless.egg-info/top_level.txt