Metadata-Version: 2.1
Name: twless
Version: 0.0.2
Summary: a coroutine framework based on twisted and stackless python
Home-page: https://github.com/konas/twless
Author: konas
Author-email: konasyan2009@gmail.com
License: UNKNOWN
Platform: UNKNOWN
Classifier: Development Status :: 1 - Planning
Classifier: Programming Language :: Python :: 2.7
Classifier: Programming Language :: Python :: 3
Classifier: License :: OSI Approved :: MIT License
Classifier: Operating System :: OS Independent
Requires-Python: >=2.7
